tokenlensai/__init__.py
tokenlensai/tokenlens.py
tokenlensai/agents/__init__.py
tokenlensai/agents/coordinator.py
tokenlensai/agents/model_comparator.py
tokenlensai/agents/results_aggregator.py
tokenlensai/agents/text_processor.py
tokenlensai/agents/token_counter.py
tokenlensai/config/__init__.py
tokenlensai/config/models.yaml
tokenlensai/tokenizers/__init__.py
tokenlensai/tokenizers/claude_tokenizer.py
tokenlensai/tokenizers/cohere_tokenizer.py
tokenlensai/tokenizers/gemini_tokenizer.py
tokenlensai/tokenizers/gpt_tokenizer.py
tokenlensai/tokenizers/llama_tokenizer.py
tokenlensai/tokenizers/mistral_tokenizer.py
tokenlensai-0.1.0.dist-info/METADATA
tokenlensai-0.1.0.dist-info/WHEEL
tokenlensai-0.1.0.dist-info/top_level.txt
tokenlensai-0.1.0.dist-info/RECORD
