Metadata-Version: 2.4
Name: TokenLensAI
Version: 0.1.0
Summary: An agentic AI-based library for token counting and analysis across multiple LLM standards
Home-page: https://github.com/tokenlens/tokenlens
Author: TokenLens Team
Author-email: tokenlens@example.com
Project-URL: Documentation, https://tokenlens.readthedocs.io
Project-URL: Bug Tracker, https://github.com/tokenlens/tokenlens/issues
Keywords: nlp,llm,tokenization,gpt,claude,llama,gemini,mistral,tokens,language models
Classifier: Development Status :: 4 - Beta
Classifier: Intended Audience :: Developers
Classifier: Intended Audience :: Science/Research
Classifier: License :: OSI Approved :: MIT License
Classifier: Programming Language :: Python :: 3
Classifier: Programming Language :: Python :: 3.8
Classifier: Programming Language :: Python :: 3.9
Classifier: Programming Language :: Python :: 3.10
Classifier: Programming Language :: Python :: 3.11
Classifier: Operating System :: OS Independent
Classifier: Topic :: Scientific/Engineering :: Artificial Intelligence
Classifier: Topic :: Software Development :: Libraries :: Python Modules
Requires-Python: >=3.8
Requires-Dist: tiktoken>=0.5.0
Requires-Dist: pyyaml>=6.0
Requires-Dist: requests>=2.28.0
Provides-Extra: dev
Requires-Dist: pytest>=7.0.0; extra == "dev"
Requires-Dist: black>=23.0.0; extra == "dev"
Requires-Dist: isort>=5.12.0; extra == "dev"
Provides-Extra: llama
Requires-Dist: llama-index>=0.9.0; extra == "llama"
Provides-Extra: all
Requires-Dist: anthropic>=0.5.0; extra == "all"
Requires-Dist: openai>=1.0.0; extra == "all"
Requires-Dist: google-generativeai>=0.3.0; extra == "all"
Requires-Dist: mistralai>=0.0.7; extra == "all"
Requires-Dist: cohere>=4.0.0; extra == "all"
Requires-Dist: llama-index>=0.9.0; extra == "all"
Dynamic: author
Dynamic: author-email
Dynamic: classifier
Dynamic: description
Dynamic: description-content-type
Dynamic: home-page
Dynamic: keywords
Dynamic: project-url
Dynamic: provides-extra
Dynamic: requires-dist
Dynamic: requires-python
Dynamic: summary
